TrackEverything/__init__.py
TrackEverything/detector.py
TrackEverything/inspector.py
TrackEverything/statistical_methods.py
TrackEverything/tool_box.py
TrackEverything/visualization_utils.py
TrackEverything-1.7.2.dist-info/LICENSE
TrackEverything-1.7.2.dist-info/METADATA
TrackEverything-1.7.2.dist-info/WHEEL
TrackEverything-1.7.2.dist-info/top_level.txt
TrackEverything-1.7.2.dist-info/RECORD
