Metadata-Version: 2.1
Name: TrackEverything
Version: 1.7.2
Summary: A package that combines detetction, classification and tracking in videos, using AI models.
Home-page: https://github.com/ami-a/TrackEverything
Author: Ami-A
Author-email: schrodingerbot@gmail.com
License: UNKNOWN
Platform: UNKNOWN
Classifier: Programming Language :: Python :: 3
Classifier: License :: OSI Approved :: MIT License
Classifier: Operating System :: OS Independent
Requires-Python: >=3.7
Requires-Dist: numpy (>=1.18.5)
Requires-Dist: scipy (>=1.4.1)
Requires-Dist: Pillow (>=7.2.0)
Requires-Dist: opencv-contrib-python (>=3.5)
